parameter_fooetal/__init__.py
parameter_fooetal/main.py
parameter_fooetal-0.1.dist-info/METADATA
parameter_fooetal-0.1.dist-info/WHEEL
parameter_fooetal-0.1.dist-info/top_level.txt
parameter_fooetal-0.1.dist-info/RECORD
