Metadata-Version: 2.1
Name: parameter-fooetal
Version: 0.1
Summary: UNKNOWN
Home-page: https://github.com/bennyantony2500/parameter_fooetal
Author: Benny Antony
Author-email: bennyantony2500@gmail.com
License: MIT
Download-URL: https://github.com/bennyantony2500/parameter_fooetal/archive/refs/tags/v_01.tar.gz
Platform: UNKNOWN
Requires-Dist: pytest
Requires-Dist: argparse
